internet_computer/__init__.py
internet_computer/tools/__init__.py
internet_computer/tools/commands.py
internet_computer/tools/inventory.py
internet_computer/tools/pymongo_fixes.py
internet_computer-0.4.0.dist-info/LICENSE
internet_computer-0.4.0.dist-info/WHEEL
internet_computer-0.4.0.dist-info/METADATA
internet_computer-0.4.0.dist-info/RECORD
