Metadata-Version: 2.1
Name: internet-computer
Version: 0.4.0
Summary: internet_computer provides tools for querying and working with the Internet Computer.
Author: Ryan Cammer
Author-email: ryancammer@gmail.com
Requires-Python: >=3.10,<4.0
Classifier: Programming Language :: Python :: 3
Classifier: Programming Language :: Python :: 3.10
Requires-Dist: PyYAML (>=6.0,<7.0)
Requires-Dist: aiohttp (>=3.8.1,<4.0.0)
Requires-Dist: pymongo (>=4.2.0,<5.0.0)
Requires-Dist: requests (>=2.28.1,<3.0.0)
